abagentsdk/__init__.py
abagentsdk/__main__.py
abagentsdk/agent_core.py
abagentsdk/cli.py
abagentsdk/config.py
abagentsdk/abagent/__init__.py
abagentsdk/core/__init__.py
abagentsdk/core/agent.py
abagentsdk/core/guardrails.py
abagentsdk/core/handoffs.py
abagentsdk/core/memory.py
abagentsdk/core/messages.py
abagentsdk/core/tools.py
abagentsdk/extensions/__init__.py
abagentsdk/extensions/handoff_prompt.py
abagentsdk/extensions/handoffs_filter.py
abagentsdk/extensions/handoffs_util.py
abagentsdk/providers/__init__.py
abagentsdk/providers/base.py
abagentsdk/providers/gemini.py
abagentsdk/providers/gemini_catalog.py
abagentsdk/providers/groq.py
abagentsdk/providers/groq_catalog.py
abagentsdk/utils/__init__.py
abagentsdk/utils/logging.py
abagentsdk/utils/silence.py
abagentsdk-0.9.2.dist-info/METADATA
abagentsdk-0.9.2.dist-info/WHEEL
abagentsdk-0.9.2.dist-info/entry_points.txt
abagentsdk-0.9.2.dist-info/top_level.txt
abagentsdk-0.9.2.dist-info/RECORD
