Metadata-Version: 2.4
Name: abagentsdk
Version: 0.9.2
Summary: The fastest way to build AI agents using Google Gemini & Groq
Home-page: https://github.com/ABZAgent/abzagentsdk
Author: Abu Bakar
License: MIT
Project-URL: Homepage, https://github.com/ABZAgent/abzagentsdk
Project-URL: Issues, https://github.com/ABZAgent/abzagentsdk/issues
Project-URL: Documentation, https://abzagent.vercel.app
Keywords: agents,gemini,google generative ai,sdk,llm,tool calling,groq
Classifier: Programming Language :: Python :: 3
Classifier: Programming Language :: Python :: 3.10
Classifier: License :: OSI Approved :: MIT License
Classifier: Operating System :: OS Independent
Classifier: Topic :: Software Development :: Libraries
Requires-Python: >=3.10
Requires-Dist: google-genai
Requires-Dist: pydantic>=2.6.0
Requires-Dist: rich>=13.7.0
Requires-Dist: python-dotenv>=1.0.1
Requires-Dist: tzdata>=2024.1; platform_system == "Windows"
Requires-Dist: typing-extensions>=4.12.0; python_version < "3.11"
Requires-Dist: groq
Dynamic: author
Dynamic: classifier
Dynamic: description
Dynamic: description-content-type
Dynamic: home-page
Dynamic: keywords
Dynamic: license
Dynamic: project-url
Dynamic: requires-dist
Dynamic: requires-python
Dynamic: summary
